{
  "arbre-de-vie-a": {
    "hero": "HeroGlowVault",
    "deck_identity": "IdentityPanel",
    "for_who": "ForWhoTwoColumns",
    "outcomes": "OutcomesBentoGrid",
    "how_to_use": "HowToNumbered",
    "in_the_box": "IncludedChecklist",
    "faq": "FaqAccordion",
    "cta_band": "CtaMarqueeRibbon"
  },
  "arbre-de-vie-b": {
    "hero": "HeroParallaxLayers",
    "deck_identity": "IdentityMinimal",
    "for_who": "ForWhoPillars",
    "outcomes": "OutcomesSignalStrip",
    "how_to_use": "HowToTimeline",
    "in_the_box": "IncludedHighlightGrid",
    "faq": "FaqTwoColumn",
    "cta_band": "CtaSplitAction"
  },
  "arbre-de-vie-c": {
    "hero": "HeroSplitImageRight",
    "deck_identity": "IdentityMinimal",
    "for_who": "ForWhoPillars",
    "outcomes": "OutcomesBentoGrid",
    "how_to_use": "HowToTimeline",
    "in_the_box": "IncludedChecklist",
    "faq": "FaqTwoColumn",
    "cta_band": "CtaSplitAction"
  },
  "arbre-de-vie-d": {
    "hero": "HeroGlowVault",
    "deck_identity": "IdentityPanel",
    "for_who": "ForWhoPillars",
    "outcomes": "OutcomesSignalStrip",
    "how_to_use": "HowToNumbered",
    "in_the_box": "IncludedHighlightGrid",
    "faq": "FaqAccordion",
    "cta_band": "CtaMarqueeRibbon"
  },
  "arbre-de-vie-e": {
    "hero": "HeroCardsFan",
    "deck_identity": "IdentityPanel",
    "for_who": "ForWhoTwoColumns",
    "outcomes": "OutcomesBentoGrid",
    "how_to_use": "HowToNumbered",
    "in_the_box": "IncludedChecklist",
    "faq": "FaqAccordion",
    "cta_band": "CtaMarqueeRibbon"
  },
  "arbre-de-vie-f": {
    "hero": "HeroCardsStrip",
    "deck_identity": "IdentityPanel",
    "for_who": "ForWhoTwoColumns",
    "outcomes": "OutcomesBentoGrid",
    "how_to_use": "HowToNumbered",
    "in_the_box": "IncludedHighlightGrid",
    "faq": "FaqAccordion",
    "cta_band": "CtaMarqueeRibbon"
  }
}
